Metadata-Version: 2.1
Name: meteor_reasoner
Version: 2.0.0
Summary: A Metric Temporal Reasoner
Home-page: https://github.com/wdimmy/MeTeoR
Author: Dingmin Wang
Author-email: dingmin.wang@cs.ox.ac.uk
License: MIT
Keywords: DatalogMTL,Knowledge Representation,Temporal Reasoning
Classifier: Topic :: Scientific/Engineering :: Artificial Intelligence
Classifier: Intended Audience :: Science/Research
Classifier: Programming Language :: Python :: 3.7
Classifier: License :: OSI Approved :: MIT License
License-File: LICENSE
Requires-Dist: outdated (>=0.2.0)
Provides-Extra: interactive
Requires-Dist: matplotlib (>=2.2.0) ; extra == 'interactive'
Requires-Dist: jupyter ; extra == 'interactive'
